pdb4all/__init__.py
pdb4all/__main__.py
pdb4all/constants.py
pdb4all/pdb.py
pdb4all/rosetta.py
pdb4all/traj.py
pdb4all-0.5.3.dist-info/LICENSE
pdb4all-0.5.3.dist-info/METADATA
pdb4all-0.5.3.dist-info/WHEEL
pdb4all-0.5.3.dist-info/entry_points.txt
pdb4all-0.5.3.dist-info/top_level.txt
pdb4all-0.5.3.dist-info/RECORD
